microsoft_skala/__init__.py
skala-1.1.1.dist-info/licenses/LICENSE.txt
skala-1.1.1.dist-info/METADATA
skala-1.1.1.dist-info/WHEEL
skala-1.1.1.dist-info/top_level.txt
skala-1.1.1.dist-info/RECORD
