Metadata-Version: 2.4
Name: skala
Version: 1.1.1
Summary: Skala Exchange Correlation Functional
Project-URL: repository, https://github.com/microsoft/skala
Classifier: Programming Language :: Python :: 3
Classifier: Development Status :: 5 - Production/Stable
Requires-Python: >=3.10
License-File: LICENSE.txt
Requires-Dist: microsoft-skala==1.1.1
Dynamic: license-file
